docker0s/__init__.py
docker0s/__main__.py
docker0s/commands.py
docker0s/config.py
docker0s/env.py
docker0s/exceptions.py
docker0s/git.py
docker0s/host.py
docker0s/manifest.py
docker0s/manifest_object.py
docker0s/path.py
docker0s/settings.py
docker0s/app/__init__.py
docker0s/app/app.py
docker0s/app/base.py
docker0s/app/names.py
docker0s/app/repo.py
docker0s-2.0.0.dist-info/LICENSE
docker0s-2.0.0.dist-info/METADATA
docker0s-2.0.0.dist-info/WHEEL
docker0s-2.0.0.dist-info/entry_points.txt
docker0s-2.0.0.dist-info/top_level.txt
docker0s-2.0.0.dist-info/RECORD
