Metadata-Version: 2.1
Name: docker0s
Version: 2.0.0
Summary: Use docker-compose to manage multiple apps on a single host
Home-page: https://radiac.net/projects/docker0s/
Author: Richard Terry
Author-email: code@radiac.net
License: BSD
Project-URL: Documentation, https://docker0s.readthedocs.io/
Project-URL: Source, https://github.com/radiac/docker0s
Project-URL: Tracker, https://github.com/radiac/docker0s/issues
Keywords: docker containers deployment
Platform: UNKNOWN
Classifier: Development Status :: 3 - Alpha
Classifier: Environment :: Web Environment
Classifier: Intended Audience :: Developers
Classifier: License :: OSI Approved :: BSD License
Classifier: Operating System :: OS Independent
Classifier: Topic :: Internet
Classifier: Programming Language :: Python
Classifier: Programming Language :: Python :: 3
Classifier: Programming Language :: Python :: 3 :: Only
Classifier: Programming Language :: Python :: 3.10
Requires-Python: >=3.10
License-File: LICENSE
Requires-Dist: click
Requires-Dist: fabric
Requires-Dist: python-dotenv
Requires-Dist: pyyaml
